{"stat.useItem.minecraft.iron_axe":17,"stat.leaveGame":3,"stat.jump":303,"stat.swimOneCm":773,"stat.fallOneCm":14493,"achievement.buildWorkBench":2,"stat.crouchOneCm":11788,"stat.craftItem.minecraft.iron_ingot":19,"stat.breakItem.minecraft.iron_pickaxe":1,"stat.useItem.minecraft.coal_ore":1,"stat.useItem.minecraft.dirt":1,"achievement.exploreAllBiomes":{"value":0,"progress":["Birch Forest Hills","Birch Forest","Ocean","River","Forest","Plains","Extreme Hills","The End","Hell"]},"stat.craftingTableInteraction":2,"stat.craftItem.minecraft.furnace":4,"stat.damageTaken":260,"stat.useItem.minecraft.furnace":4,"stat.flyOneCm":60720,"achievement.buildPickaxe":2,"stat.mineBlock.minecraft.gravel":1,"stat.damageDealt":840,"achievement.buildBetterPickaxe":2,"stat.mineBlock.minecraft.iron_ore":19,"stat.timeSinceDeath":22986,"stat.useItem.minecraft.iron_pickaxe":320,"stat.mineBlock.minecraft.dirt":1,"stat.useItem.minecraft.crafting_table":1,"stat.killEntity.Pig":1,"stat.walkOneCm":84420,"stat.useItem.minecraft.bread":9,"stat.useItem.minecraft.cobblestone":8,"stat.craftItem.minecraft.crafting_table":1,"stat.furnaceInteraction":9,"stat.useItem.minecraft.gravel":1,"stat.mineBlock.minecraft.coal_ore":15,"stat.killEntity.Creeper":1,"achievement.mineWood":18,"stat.sprintOneCm":43201,"stat.craftItem.minecraft.stick":4,"stat.killEntity.Skeleton":1,"achievement.openInventory":19,"stat.useItem.minecraft.iron_sword":12,"stat.craftItem.minecraft.planks":260,"stat.mobKills":3,"stat.mineBlock.minecraft.log":15,"stat.mineBlock.minecraft.leaves":5,"stat.playOneMinute":22986,"stat.craftItem.minecraft.iron_pickaxe":1,"stat.mineBlock.minecraft.stone":285,"stat.mineBlock.minecraft.tallgrass":4,"stat.diveOneCm":266}